castodia/__init__.py
castodia-0.0.4.4.dist-info/LICENSE
castodia-0.0.4.4.dist-info/METADATA
castodia-0.0.4.4.dist-info/WHEEL
castodia-0.0.4.4.dist-info/top_level.txt
castodia-0.0.4.4.dist-info/RECORD
